{
  "count": 4,
  "next": null,
  "previous": null,
  "results": [
    {
      "id": 10001450,
      "image": "https://picsum.photos/seed/ss13/588/419",
      "width": 588,
      "height": 419,
      "is_deleted": false
    },
    {
      "id": 10001451,
      "image": "https://picsum.photos/seed/ss14/588/419",
      "width": 588,
      "height": 419,
      "is_deleted": false
    },
    {
      "id": 10001452,
      "image": "https://picsum.photos/seed/ss15/588/419",
      "width": 588,
      "height": 419,
      "is_deleted": false
    },
    {
      "id": 10001453,
      "image": "https://picsum.photos/seed/ss16/588/419",
      "width": 588,
      "height": 419,
      "is_deleted": false
    }
  ]
}
